django_concurrent_test/__init__.py
django_concurrent_test/db.py
django_concurrent_test/exceptions.py
django_concurrent_test/middleware.py
django_concurrent_test/pytest_plugin.py
django_concurrent_test/runner.py
django_concurrent_test/security.py
django_concurrent_test/timing_utils.py
django_concurrent_test-1.0.0.dist-info/licenses/AUTHORS.md
django_concurrent_test-1.0.0.dist-info/licenses/LICENSE
django_concurrent_test-1.0.0.dist-info/METADATA
django_concurrent_test-1.0.0.dist-info/WHEEL
django_concurrent_test-1.0.0.dist-info/entry_points.txt
django_concurrent_test-1.0.0.dist-info/top_level.txt
django_concurrent_test-1.0.0.dist-info/RECORD
