Metadata-Version: 2.4
Name: django-concurrent-test
Version: 1.0.0
Summary: Production-ready Django package for safe and configurable concurrent testing with isolated databases, timing analytics, and concurrency simulation middleware
Home-page: https://github.com/example/django-concurrent-test
Author: Django Concurrent Test Team
Author-email: Rana Ehtasham Ali <ranaehtashamali1@gmail.com>
Maintainer-email: Rana Ehtasham Ali <ranaehtashamali1@gmail.com>
License: MIT
Project-URL: Homepage, https://github.com/RanaEhtashamAli/django-concurrent-test
Project-URL: Documentation, https://django-concurrent-test.readthedocs.io
Project-URL: Repository, https://github.com/RanaEhtashamAli/django-concurrent-test
Project-URL: Bug Tracker, https://github.com/RanaEhtashamAli/django-concurrent-test/issues
Project-URL: Changelog, https://github.com/RanaEhtashamAli/django-concurrent-test/blob/main/CHANGELOG.md
Keywords: django,testing,concurrent,parallel,database,postgresql,mysql,middleware,analytics,benchmarking
Classifier: Development Status :: 5 - Production/Stable
Classifier: Intended Audience :: Developers
Classifier: License :: OSI Approved :: MIT License
Classifier: Operating System :: OS Independent
Classifier: Programming Language :: Python :: 3
Classifier: Programming Language :: Python :: 3.9
Classifier: Programming Language :: Python :: 3.10
Classifier: Programming Language :: Python :: 3.11
Classifier: Framework :: Django
Classifier: Framework :: Django :: 3.2
Classifier: Framework :: Django :: 4.2
Classifier: Framework :: Django :: 5.0
Classifier: Topic :: Software Development :: Testing
Classifier: Topic :: Software Development :: Libraries :: Python Modules
Classifier: Topic :: Software Development :: Quality Assurance
Requires-Python: >=3.8
License-File: LICENSE
License-File: AUTHORS.md
Requires-Dist: Django<5.1,>=3.2
Requires-Dist: psycopg2-binary>=2.9.0; sys_platform != "win32"
Requires-Dist: psycopg2>=2.9.0; sys_platform == "win32"
Requires-Dist: mysqlclient>=2.1.0
Requires-Dist: pytest>=7.0.0
Requires-Dist: pytest-django>=4.5.0
Requires-Dist: psutil>=5.8.0
Provides-Extra: dev
Requires-Dist: pytest>=7.0.0; extra == "dev"
Requires-Dist: pytest-cov>=4.0.0; extra == "dev"
Requires-Dist: pytest-xdist>=3.0.0; extra == "dev"
Requires-Dist: black>=22.0.0; extra == "dev"
Requires-Dist: flake8>=5.0.0; extra == "dev"
Requires-Dist: mypy>=1.0.0; extra == "dev"
Requires-Dist: isort>=5.0.0; extra == "dev"
Requires-Dist: bandit>=1.7.0; extra == "dev"
Requires-Dist: safety>=2.0.0; extra == "dev"
Provides-Extra: test
Requires-Dist: pytest>=7.0.0; extra == "test"
Requires-Dist: pytest-cov>=4.0.0; extra == "test"
Requires-Dist: pytest-django>=4.5.0; extra == "test"
Requires-Dist: djangorestframework>=3.14.0; extra == "test"
Provides-Extra: benchmark
Requires-Dist: pytest-benchmark>=4.0.0; extra == "benchmark"
Dynamic: author
Dynamic: home-page
Dynamic: license-file
Dynamic: requires-python
